{"api":{"detailsUri":"https://services.epicurious.com/api/recipes/v3/detail","facetUri":"https://services.epicurious.com/api/search/v1/facets","searchUri":"https://services.epicurious.com/api/search/v1/query","suggestUri":"https://services.epicurious.com/api/search/v1/suggest"},"inputTerms":"","searchTerms":"","facets":{"content":{"article":2993,"undefined":37,"cnevideo":1031,"gallery":787,"menu":265,"package":98,"recipe":34975},"cuisine":{"african":{"count":102},"american":{"count":5504},"argentine":{"count":31},"ashkenazi":{"count":13},"asian":{"count":1385},"australian-new-zealand":{"count":20},"basque":{"count":13},"brazilian":{"count":27},"british":{"count":40},"cajun-creole":{"count":202},"californian":{"count":34},"canadian":{"count":16},"cantonese":{"count":1},"central-american-caribbean":{"count":215},"central-asian":{"count":3},"central-south-american":{"count":163},"chinese":{"count":308},"cuban":{"count":49},"eastern-european-russian":{"count":175},"english":{"count":252},"ethiopian":{"count":5},"european":{"count":161},"french":{"count":1394},"french-provencal":{"count":57},"german":{"count":101},"greek":{"count":297},"indian":{"count":404},"indonesian":{"count":18},"irish":{"count":128},"israeli":{"count":34},"italian":{"count":2307},"italian-american":{"count":210},"japanese":{"count":226},"jewish":{"count":418},"korean":{"count":103},"latin-american":{"count":249},"mediterranean":{"count":467},"mexican":{"count":951},"middle-eastern":{"count":394},"midwestern":{"count":23},"moroccan":{"count":196},"new-england":{"count":57},"northern-italian":{"count":28},"nuevo-latino":{"count":59},"pacific-northwest":{"count":13},"scandinavian":{"count":139},"scottish":{"count":5},"sephardic":{"count":18},"south-american":{"count":54},"south-asian":{"count":38},"southeast-asian":{"count":113},"southern":{"count":354},"southern-italian":{"count":26},"southwestern":{"count":243},"spanish-portuguese":{"count":375},"sushi":{"count":8},"szechuan-hunan":{"count":8},"tex-mex":{"count":138},"thai":{"count":243},"turkish":{"count":39},"vietnamese":{"count":114}},"ingredient":{"almond":{"count":970},"amaretto":{"count":52},"anchovy":{"count":72},"anise":{"count":165},"apple":{"count":1029},"apple-juice":{"count":14},"apricot":{"count":364},"artichoke":{"count":243},"arugula":{"count":413},"asian-pear":{"count":25},"asparagus":{"count":338},"avocado":{"count":419},"bacon":{"count":899},"banana":{"count":305},"barley":{"count":78},"basil":{"count":829},"bass":{"count":117},"bean":{"count":1075},"beef":{"count":1200},"beef-rib":{"count":90},"beef-shank":{"count":15},"beef-tenderloin":{"count":81},"beer":{"count":206},"beet":{"count":337},"bell-pepper":{"count":1066},"berry":{"count":679},"bitters":{"count":201},"blackberry":{"count":208},"blue-cheese":{"count":338},"blueberry":{"count":281},"bok-choy":{"count":76},"bourbon":{"count":204},"bran":{"count":13},"brandy":{"count":410},"breadcrumbs":{"count":99},"brie":{"count":37},"brisket":{"count":54},"broccoli":{"count":203},"broccoli-rabe":{"count":55},"brown-rice":{"count":25},"brussel-sprout":{"count":109},"brussels-sprout":{"count":109},"buffalo":{"count":13},"bulgur":{"count":71},"butter":{"count":424},"buttermilk":{"count":149},"butternut-squash":{"count":234},"butterscotch-caramel-recipes":{"count":22},"cabbage":{"count":481},"calvados":{"count":46},"campari":{"count":37},"cantaloupe":{"count":73},"capers":{"count":290},"caraway":{"count":73},"cardamom":{"count":79},"carrot":{"count":1014},"cashew":{"count":99},"cauliflower":{"count":182},"caviar":{"count":6},"celery":{"count":442},"chambord":{"count":18},"champagne":{"count":199},"chard":{"count":139},"chartreuse":{"count":26},"cheddar":{"count":388},"cheese":{"count":2308},"cherry":{"count":431},"chestnut":{"count":116},"chicken":{"count":2080},"chickpea":{"count":244},"chile-pepper":{"count":370},"chive":{"count":336},"chocolate":{"count":2078},"cilantro":{"count":826},"cinnamon":{"count":787},"citrus":{"count":1169},"clam":{"count":214},"clove":{"count":262},"coconut":{"count":592},"cod":{"count":111},"coffee":{"count":409},"cognac-armagnac":{"count":129},"collard-greens":{"count":57},"condiment":{"count":170},"coriander":{"count":181},"corn":{"count":621},"cornmeal":{"count":412},"cottage-cheese":{"count":44},"couscous":{"count":135},"crab":{"count":256},"cranberry":{"count":519},"cream-cheese":{"count":556},"creme-de-cacao":{"count":30},"creme-de-menthe":{"count":3},"cucumber":{"count":585},"cumin":{"count":122},"currant":{"count":165},"curry":{"count":402},"dairy":{"count":2413},"dark-chocolate":{"count":8},"date":{"count":176},"dill":{"count":408},"dried-fruit":{"count":279},"duck":{"count":153},"eau-de-vie":{"count":14},"egg":{"count":3068},"eggplant":{"count":354},"endive":{"count":179},"escarole":{"count":88},"fennel":{"count":541},"feta":{"count":337},"fig":{"count":205},"fish":{"count":1388},"fontina":{"count":76},"fortified-wine":{"count":142},"frangelico":{"count":27},"fruit":{"count":2805},"fruit-juice":{"count":564},"game":{"count":53},"garlic":{"count":2308},"gin":{"count":421},"ginger":{"count":1575},"goat-cheese":{"count":393},"goose":{"count":14},"gouda":{"count":16},"grains":{"count":20},"grand-marnier":{"count":5},"granola":{"count":11},"grape":{"count":171},"grapefruit":{"count":202},"grappa":{"count":9},"green-bean":{"count":349},"green-onion-scallion":{"count":169},"grenadine":{"count":2},"ground-beef":{"count":162},"ground-lamb":{"count":39},"guava":{"count":27},"halibut":{"count":128},"ham":{"count":339},"hazelnut":{"count":352},"herb":{"count":2257},"hominy-cornmeal-masa":{"count":130},"honey":{"count":629},"honeydew":{"count":47},"horseradish":{"count":224},"hot-pepper":{"count":618},"jalapeno":{"count":463},"jam-or-jelly":{"count":246},"jerusalem-artichoke":{"count":26},"jicama":{"count":53},"kahlua":{"count":37},"kale":{"count":226},"kirsch":{"count":43},"kiwi":{"count":47},"kumquat":{"count":54},"lamb":{"count":507},"lamb-chop":{"count":58},"lamb-shank":{"count":24},"leafy-green":{"count":1301},"leek":{"count":392},"legume":{"count":130},"lemon":{"count":1794},"lemon-juice":{"count":195},"lemongrass":{"count":109},"lentil":{"count":180},"lettuce":{"count":369},"lima-bean":{"count":65},"lime":{"count":782},"lime-juice":{"count":189},"lingonberry":{"count":10},"liqueur":{"count":445},"lobster":{"count":132},"lychee":{"count":12},"macadamia-nut":{"count":66},"mango":{"count":331},"maple-syrup":{"count":261},"marsala":{"count":55},"marscarpone":{"count":8},"marshmallow":{"count":25},"marzipan":{"count":1},"mayonnaise":{"count":520},"meat":{"count":471},"melon":{"count":84},"mezcal":{"count":3},"midori":{"count":6},"milk-cream":{"count":3063},"mint":{"count":884},"molasses":{"count":188},"monterey-jack":{"count":85},"mozzarella":{"count":291},"mushroom":{"count":1316},"mussel":{"count":169},"mustard":{"count":737},"mustard-greens":{"count":56},"nectarine":{"count":85},"noodle":{"count":275},"nut":{"count":1440},"nutmeg":{"count":179},"oat":{"count":228},"oatmeal":{"count":23},"octopus":{"count":17},"okra":{"count":50},"olive":{"count":820},"onion":{"count":3011},"orange":{"count":1224},"orange-juice":{"count":71},"oregano":{"count":153},"orzo":{"count":6},"oyster":{"count":81},"papaya":{"count":67},"paprika":{"count":92},"parmesan":{"count":1038},"parsley":{"count":756},"parsnip":{"count":200},"passion-fruit":{"count":59},"pasta":{"count":1571},"pea":{"count":377},"peach":{"count":333},"peanut":{"count":326},"peanut-butter":{"count":64},"pear":{"count":453},"pecan":{"count":602},"pepper":{"count":894},"pernod":{"count":69},"persimmon":{"count":38},"phyllo-puff-pastry-dough":{"count":245},"pine-nut":{"count":335},"pineapple":{"count":391},"pistachio":{"count":268},"plantain":{"count":41},"plum":{"count":181},"poblano":{"count":10},"pomegranate":{"count":125},"pomegranate-juice":{"count":21},"poppy":{"count":50},"pork":{"count":1397},"pork-chop":{"count":135},"pork-rib":{"count":78},"pork-tenderloin":{"count":143},"port":{"count":163},"potato":{"count":1913},"poultry":{"count":821},"poultry-sausage":{"count":24},"prosciutto":{"count":255},"prune":{"count":128},"pumpkin":{"count":273},"quail":{"count":23},"quince":{"count":43},"quinoa":{"count":83},"rabbit":{"count":20},"rack-of-lamb":{"count":35},"radicchio":{"count":47},"radish":{"count":274},"raisin":{"count":475},"raspberry":{"count":507},"red-wine":{"count":380},"rhubarb":{"count":142},"rice":{"count":851},"ricotta":{"count":277},"root-vegetable":{"count":290},"rose":{"count":9},"rosemary":{"count":498},"rum":{"count":539},"rutabaga":{"count":56},"rye":{"count":30},"saffron":{"count":161},"sage":{"count":275},"sake":{"count":40},"salmon":{"count":506},"sardine":{"count":11},"sausage":{"count":615},"scallop":{"count":256},"scotch":{"count":54},"seafood":{"count":607},"seed":{"count":234},"semolina":{"count":20},"sesame":{"count":215},"sesame-oil":{"count":49},"shallot":{"count":475},"shellfish":{"count":825},"sherry":{"count":193},"shrimp":{"count":798},"snapper":{"count":86},"sour-cream":{"count":558},"soy":{"count":181},"soy-sauce":{"count":380},"sparkling-wine":{"count":85},"spice":{"count":1033},"spinach":{"count":587},"spirit":{"count":368},"squash":{"count":262},"squid":{"count":79},"steak":{"count":395},"strawberry":{"count":523},"sugar-snap-pea":{"count":122},"sweet-potato-yam":{"count":388},"swiss-cheese":{"count":100},"swordfish":{"count":24},"tamarind":{"count":42},"tangerine":{"count":63},"tapioca":{"count":24},"tarragon":{"count":312},"tea":{"count":174},"tequila":{"count":138},"thyme":{"count":462},"tilapia":{"count":15},"tofu":{"count":134},"tomatillo":{"count":105},"tomato":{"count":3239},"tortillas":{"count":245},"tree-nut":{"count":149},"triple-sec":{"count":104},"tropical-fruit":{"count":91},"trout":{"count":86},"truffle":{"count":1},"truffle-oil":{"count":1},"tuna":{"count":197},"turkey":{"count":578},"turnip":{"count":148},"vanilla":{"count":463},"veal":{"count":201},"vegetable":{"count":3066},"venison":{"count":17},"vermouth":{"count":29},"vinegar":{"count":834},"vodka":{"count":225},"walnut":{"count":743},"wasabi":{"count":30},"watercress":{"count":233},"watermelon":{"count":118},"whiskey":{"count":123},"white-chocolate":{"count":11},"white-wine":{"count":677},"whole-wheat":{"count":62},"wild-rice":{"count":26},"wine":{"count":293},"yellow-squash":{"count":46},"yogurt":{"count":726},"yuca":{"count":15},"zucchini":{"count":487}},"meal":{"appetizer":{"count":2894},"breakfast":{"count":1573},"brunch":{"count":1802},"buffet":{"count":232},"dessert":{"count":7414},"dinner":{"count":4887},"drink":{"count":2142},"hors-doeuvre":{"count":39},"lunch":{"count":2509},"one-pot-meal":{"count":26},"side":{"count":5770}},"occasion":{"anniversary":{"count":254},"back-to-school":{"count":461},"backyard-bbq":{"count":1596},"bastille-day":{"count":56},"birthday":{"count":486},"christmas":{"count":2004},"christmas-eve":{"count":666},"cinco-de-mayo":{"count":309},"cocktail-party":{"count":2259},"diwali":{"count":32},"easter":{"count":467},"engagement-party":{"count":416},"entertaining":{"count":20},"fall":{"count":5127},"family-reunion":{"count":654},"fathers-day":{"count":581},"fourth-of-july":{"count":696},"friendsgiving":{"count":9},"graduation":{"count":180},"halloween":{"count":150},"hanukkah":{"count":195},"kentucky-derby":{"count":93},"kwanzaa":{"count":32},"labor-day":{"count":11},"lunar-new-year":{"count":91},"mardi-gras":{"count":124},"mothers-day":{"count":406},"new-years-day":{"count":174},"new-years-eve":{"count":349},"oktoberfest":{"count":60},"oscars":{"count":271},"party":{"count":1875},"passover":{"count":307},"persian-new-year":{"count":15},"picnic":{"count":987},"poker-game-night":{"count":344},"potluck":{"count":1066},"purim":{"count":29},"ramadan":{"count":83},"rosh-hashanah-yom-kippur":{"count":152},"shavuot":{"count":46},"shower":{"count":726},"spring":{"count":2913},"st-patricks-day":{"count":132},"sukkot":{"count":31},"summer":{"count":7034},"super-bowl":{"count":630},"tailgating":{"count":284},"thanksgiving":{"count":2383},"valentines-day":{"count":564},"wedding":{"count":216},"winter":{"count":5142}},"special-consideration":{"dairy-free":{"count":5949},"diabetes-friendly":{"count":204},"fat-free":{"count":691},"healthy":{"count":4007},"high-fiber":{"count":1805},"kid-friendly":{"count":4016},"kidney-friendly":{"count":5345},"kosher":{"count":12757},"kosher-for-passover":{"count":71},"low-cal":{"count":1888},"low-carb":{"count":585},"low-cholesterol":{"count":775},"low-fat":{"count":1561},"low-no-sugar":{"count":500},"low-sodium":{"count":692},"low-sugar":{"count":26},"no-sugar-added":{"count":5913},"organic":{"count":12},"paleo":{"count":1429},"peanut-free":{"count":16620},"pescatarian":{"count":12524},"quick-and-easy":{"count":9578},"raw":{"count":138},"soy-free":{"count":16235},"sugar-conscious":{"count":4950},"tree-nut-free":{"count":14118},"vegan":{"count":3426},"vegetarian":{"count":13545},"wheat-gluten-free":{"count":9436}},"technique":{"advance-prep-required":{"count":228},"bake":{"count":8371},"boil":{"count":712},"braise":{"count":471},"brine":{"count":55},"broil":{"count":794},"chill":{"count":1857},"deep-fry":{"count":160},"freeze-chill":{"count":683},"fry":{"count":826},"grill-barbecue":{"count":1672},"marinate":{"count":850},"no-cook":{"count":1791},"pan-fry":{"count":401},"poach":{"count":235},"roast":{"count":1986},"saute":{"count":3184},"simmer":{"count":1306},"steam":{"count":357},"stew":{"count":263},"stir-fry":{"count":312}},"tag":{"22-minute-meals":{"count":26},"3-ingredient-recipes":{"count":69},"30-days-of-groceries":{"count":10},"cakeweek":{"count":6},"camping":{"count":2},"cheese-week":{"count":38},"cook-like-a-diner":{"count":5},"cook90":{"count":10},"cookbook-critic":{"count":4},"cookbooks":{"count":10},"cooking-after-dark":{"count":3},"dinner-1-2-3":{"count":3},"drinks":{"count":27},"epi-loves-the-microwave":{"count":2},"epi-ushg":{"count":3},"flaming-hot-summer":{"count":13},"frankenrecipe":{"count":14},"freezer-food":{"count":5},"gluten-free-and-fresh":{"count":5},"house-cocktail":{"count":15},"iced-coffee":{"count":3},"kitchen-intelligence":{"count":1},"kitchen-olympics":{"count":1},"leftovers":{"count":12},"microwave":{"count":4},"no-meat-no-problem":{"count":21},"pasta-week":{"count":1},"pickles":{"count":29},"quick-and-healthy":{"count":132},"sandwich-theory":{"count":16},"sauce-secrets":{"count":25},"small-plates":{"count":33},"snack":{"count":86},"snack-week":{"count":42},"sourdough":{"count":2},"sunday-stash":{"count":2},"taco":{"count":18},"takeout-at-home":{"count":7},"tested-and-improved":{"count":3},"wasteless":{"count":2}},"type":{"alcoholic":{"count":1612},"aperitif":{"count":27},"biscuit":{"count":10},"bread":{"count":1104},"brownie":{"count":9},"burrito":{"count":1},"cake":{"count":1521},"candy":{"count":213},"casserole-gratin":{"count":310},"cheesecake":{"count":4},"chili":{"count":7},"cobbler-crumble":{"count":10},"cocktail":{"count":837},"condiment-spread":{"count":1289},"cookie":{"count":853},"cranberry-sauce":{"count":5},"crepe":{"count":2},"cupcake":{"count":20},"custard":{"count":6},"digestif":{"count":12},"dip":{"count":37},"edible-gift":{"count":288},"egg-nog":{"count":15},"flat-bread":{"count":11},"frittata":{"count":4},"fritter":{"count":2},"frozen-dessert":{"count":722},"guacamole":{"count":1},"hamburger":{"count":12},"hot-drink":{"count":99},"hummus":{"count":5},"ice-cream":{"count":29},"iced-tea":{"count":26},"lasagna":{"count":6},"macaroni-and-cheese":{"count":6},"margarita":{"count":34},"marinade":{"count":3},"martini":{"count":38},"meatball":{"count":15},"meatloaf":{"count":3},"muffin":{"count":8},"non-alcoholic":{"count":453},"omelet":{"count":4},"pancake":{"count":10},"pastry":{"count":201},"pie":{"count":39},"pizza":{"count":23},"pot-pie":{"count":3},"potato-salad":{"count":2},"punch":{"count":98},"quiche":{"count":4},"risotto":{"count":2},"rub":{"count":3},"salad":{"count":2555},"salad-dressing":{"count":240},"salsa":{"count":17},"sandwich":{"count":724},"sangria":{"count":28},"sauce":{"count":1322},"skewer":{"count":11},"smoothie":{"count":76},"sorbet":{"count":1},"souffle-meringue":{"count":6},"soup-stew":{"count":1923},"spritzer":{"count":27},"stock":{"count":10},"stuffing-dressing":{"count":186},"tart":{"count":16},"waffle":{"count":7}}},"items":[{"id":"54a4507c19925f464b38de9f","dek":"","hed":"Cinnamon-Sugar","pubDate":"2004-08-20T04:00:00.000Z","author":[{"name":"Rozanne Gold"}],"type":"recipe","url":"/recipes/food/views/cinnamon-sugar-108994","photoData":{"id":"5674617eb47c050a284a4e11","filename":"EP_12162015_placeholders_bright.jpg","caption":"Menu Placeholder 1","credit":"Photo by Chelsea Kyle, Prop Styling by Anna Stockwell","colors":{"average":"#000000"},"type":"photo"},"tag":{"category":"type","name":"Condiment/Spread","url":"","photosBadgeAltText":"","photosBadgeFileName":"","photosBadgeID":"","photosBadgeRelatedUri":""},"aggregateRating":0,"ingredients":["2 cups granualted sugar","3 tablespoons good-quality ground cinnamon"],"prepSteps":["Place sugar in a small bowl. Stir in cinnamon and mix thoroughly. Transfer to a jar or container with a tight-fitting cover. Lasts indefinitely."],"reviewsCount":0,"willMakeAgainPct":0},{"id":"54a4507c19925f464b38de9d","dek":"","hed":"Sake-Steamed Halibut with Dilled Carrots","pubDate":"2004-08-20T04:00:00.000Z","author":[],"type":"recipe","url":"/recipes/food/views/sake-steamed-halibut-with-dilled-carrots-107141","photoData":{"id":"560ea139f3a00aeb2f1d6b73","filename":"107141.jpg","caption":"Sake-Steamed Halibut with Dilled Carrots","credit":"Scott Peterson","promoTitle":"Sake-Steamed Halibut with Dilled Carrots","title":"Sake-Steamed Halibut with Dilled Carrots","orientation":"portrait","restrictCropping":false},"tag":{"category":"cuisine","name":"Japanese","url":"","photosBadgeAltText":"","photosBadgeFileName":"","photosBadgeID":"","photosBadgeRelatedUri":""},"aggregateRating":3,"ingredients":["Nonstick vegetable oil spray","2 10- to 12-ounce halibut fillets (each about 1 1/2 inches thick)","4 teaspoons chopped fresh dill","1 750-ml bottle sake","3 1/2-inch-thick onion slices","2 cups thinly sliced peeled carrots","2 garlic cloves, peeled, halved","1 teaspoon butter"],"prepSteps":["Spray steamer rack with nonstick spray. Sprinkle both sides of halibut with salt and pepper, then sprinkle top of fillets with 2 teaspoons dill; place fish on prepared steamer rack.","Combine sake and onion in large pot; bring to boil. Continue to boil 2 minutes. Add carrots and garlic to pot; return to boil. Place steamer rack with fish over liquid in pot. Cover pot tightly and steam fish until just opaque in center, about 8 minutes. Transfer fish to platter. Cut each fillet crosswise in half; cover with foil. Discard onion. Using slotted spoon, transfer carrots and garlic to small bowl; mix in butter and remaining 2 teaspoons dill. Season with salt and pepper. Spoon carrots alongside fish on platter. Boil liquid in pot until reduced to 6 tablespoons, about 3 minutes. Pour over fish and carrots."],"reviewsCount":7,"willMakeAgainPct":100},{"id":"54a4525219925f464b38eb0d","dek":"Active time: 40 min Start to finish: 40 min","hed":"Jerusalem Artichoke Soup with Pumpernickel Croutons","pubDate":"2004-08-20T04:00:00.000Z","author":[],"type":"recipe","url":"/recipes/food/views/jerusalem-artichoke-soup-with-pumpernickel-croutons-107401","photoData":{"id":"56746183b47c050a284a4e15","filename":"EP_12162015_placeholders_formal.jpg","caption":"Menu Placeholder 2","credit":"Photo by Chelsea Kyle, Prop Styling by Rhoda Boone","colors":{"average":"#000000"},"type":"photo"},"tag":{"category":"type","name":"Soup/Stew","url":"","photosBadgeAltText":"","photosBadgeFileName":"","photosBadgeID":"","photosBadgeRelatedUri":""},"aggregateRating":3.1,"ingredients":["1 (1/4-inch-thick) slice pumpernickel bread, crust discarded and bread cut into 1/4-inch dice","1 1/2 lb Jerusalem artichokes (sometimes called Sun Chokes)","1 1/2 cups nonfat (skim) milk","1/2 cup water","1/2 teaspoon salt","1/8 teaspoon black pepper","Garnish: 2 tablespoons chopped fresh flat-leaf parsley"],"prepSteps":["Preheat oven to 400°F.","Toast bread in a shallow baking pan in middle of oven, stirring once or twice, until crisp, about 7 minutes.","Peel artichokes with a vegetable peeler and cut into 1-inch pieces, then simmer in milk and water in a 3-quart heavy saucepan, partially covered (be careful not to let it boil over), stirring occasionally, until artichokes are very tender, about 15 minutes.","Purée artichokes with cooking liquid, salt, and pepper in 2 batches in a blender until smooth (use caution when blending hot liquids). Transfer purée to same saucepan and thin with additional water if necessary. Heat soup over moderate heat, stirring, until hot. Serve topped with croutons and parsley."],"reviewsCount":8,"willMakeAgainPct":75},{"id":"54a452516529d92b2c01f26e","dek":"","hed":"Heirloom Tomato Salad with Blue Cheese","pubDate":"2004-08-20T04:00:00.000Z","author":[],"type":"recipe","url":"/recipes/food/views/heirloom-tomato-salad-with-blue-cheese-108427","photoData":{"id":"560df8e9f9a84192308a8ce2","filename":"108427.jpg","caption":"Heirloom Tomato Salad with Blue Cheese","credit":"Mark Thomas","promoTitle":"Heirloom Tomato Salad with Blue Cheese","title":"Heirloom Tomato Salad with Blue Cheese","orientation":"portrait","restrictCropping":false},"tag":{"category":"cuisine","name":"American","url":"","photosBadgeAltText":"","photosBadgeFileName":"","photosBadgeID":"","photosBadgeRelatedUri":""},"aggregateRating":3.55,"ingredients":["8 1/2-inch-thick slices crusty bread","4 large garlic cloves, halved","3 tablespoons plus 1/3 cup extra-virgin olive oil","1 cup currant or grape tomatoes or halved cherry or pear tomatoes","1/2 cup chopped green onions","10 medium heirloom tomatoes of assorted colors, cored, thinly sliced","1 small red onion, sliced paper-thin","3 celery stalks, sliced thin on diagonal","1 1/2 cups coarsely crumbled blue cheese"],"prepSteps":["Prepare barbecue (medium-high heat). Rub bread with cut garlic halves; brush bread with 3 tablespoons oil. Combine remaining 1/3 cup oil, currant tomatoes, and green onions in medium bowl; toss to coat. Season with salt and pepper.","Overlap tomato slices in concentric circles on platter, alternating colors. Scatter onion and celery slices over tomatoes. Sprinkle with salt and pepper. Spoon tomato and green onion mixture over. Sprinkle with crumbled cheese.","Grill bread until golden, about 2 minutes per side. Cut each slice diagonally in half; serve with salad."],"reviewsCount":39,"willMakeAgainPct":89},{"id":"54a452516529d92b2c01f26b","dek":"","hed":"Roasted Red Pepper Corn Bread","pubDate":"2004-08-20T04:00:00.000Z","author":[],"type":"recipe","url":"/recipes/food/views/roasted-red-pepper-corn-bread-107256","photoData":{"id":"56746182accb4c9831e45e0a","filename":"EP_12162015_placeholders_rustic.jpg","caption":"Menu Placeholder 3","credit":"Photo by Chelsea Kyle, Prop Styling by Anna Stockwell","colors":{"average":"#000000"},"type":"photo"},"tag":{"category":"type","name":"Bread","url":"","photosBadgeAltText":"","photosBadgeFileName":"","photosBadgeID":"","photosBadgeRelatedUri":""},"aggregateRating":3.17,"ingredients":["1 large red bell pepper","2 cups yellow cornmeal","1 cup unbleached all purpose flour","1/3 cup sugar","4 teaspoons baking powder","1 teaspoon salt","1 1/2 cups buttermilk","1/2 cup (1 stick) unsalted butter, melted, cooled to lukewarm","2 large eggs, beaten to blend"],"prepSteps":["Preheat oven to 400°F. Butter 13x9x2-inch metal baking pan. Char pepper directly over gas flame or in broiler until blackened on all sides. Enclose in paper bag; let stand 10 minutes. Peel, seed, and coarsely chop pepper.","Whisk cornmeal and next 4 ingredients in bowl to blend. Add buttermilk, butter, and eggs. Stir just to moisten. Mix in bell pepper; transfer to prepared pan. Bake bread until tester inserted into center comes out clean, about 20 minutes. Cool in pan. (Can be made 1 day ahead. Cover and store at room temperature.)"],"reviewsCount":5,"willMakeAgainPct":100},{"id":"54a4525119925f464b38eafe","dek":"","hed":"Raspberry, Strawberry, and Orange Granita","pubDate":"2004-08-20T04:00:00.000Z","author":[],"type":"recipe","url":"/recipes/food/views/raspberry-strawberry-and-orange-granita-105389","photoData":{"id":"5674617e47d1a28026045e4f","filename":"EP_12162015_placeholders_casual.jpg","caption":"Menu Placeholder 4","credit":"Photo by Chelsea Kyle, Prop Styling by Rhoda Boone","colors":{"average":"#000000"},"type":"photo"},"tag":{"category":"ingredient","name":"Fruit","url":"","photosBadgeAltText":"","photosBadgeFileName":"","photosBadgeID":"","photosBadgeRelatedUri":""},"aggregateRating":3,"ingredients":["1 cup orange juice","3/4 cup water","1/2 cup honey","1/4 cup sugar","1 teaspoon grated orange peel","1 16-ounce package fresh strawberries, hulled, quartered (about 3 1/2 cups)","2 1/2-pint baskets fresh raspberries"],"prepSteps":["Combine orange juice, 3/4 cup water, honey, sugar, and orange peel in blender. Add half of strawberries and half of raspberries; puree until almost smooth. Add remaining berries; puree until smooth. Pour mixture out onto 13x9x2-inch baking pan. Freeze until edges are icy and center is slushy, about 1 hour 30 minutes. Stir icy edges into slushy center. Freeze granita until solid, stirring every 45 minutes, about 3 1/2 hours longer.","Using fork, scrape granita down length of pan, forming icy flakes. Cover and freeze at least 1 hour and up to 2 days. Spoon granita into glasses."],"reviewsCount":1,"willMakeAgainPct":100},{"id":"54a452506529d92b2c01f264","dek":"Purchased Mexican wedding cookies or any buttery nut cookie would be good with this dessert.","hed":"Raspberry-Plum Sorbet","pubDate":"2004-08-20T04:00:00.000Z","author":[],"type":"recipe","url":"/recipes/food/views/raspberry-plum-sorbet-105388","photoData":{"id":"5674617eb47c050a284a4e11","filename":"EP_12162015_placeholders_bright.jpg","caption":"Menu Placeholder 1","credit":"Photo by Chelsea Kyle, Prop Styling by Anna Stockwell","colors":{"average":"#000000"},"type":"photo"},"tag":{"category":"ingredient","name":"Fruit","url":"","photosBadgeAltText":"","photosBadgeFileName":"","photosBadgeID":"","photosBadgeRelatedUri":""},"aggregateRating":3.25,"ingredients":["1 1/3 cups sugar","1 1/3 cups water","2 pounds plums, pitted, cut into large chunks","3 1/2 cups fresh raspberries or frozen unsweetened raspberries, thawed"],"prepSteps":["Combine sugar and water in medium saucepan. Bring to boil, stirring to dissolve sugar. Remove from heat. Cool sugar syrup completely.","Blend plums and raspberries in processor until smooth. Strain through coarse sieve into large bowl, pressing on solids to extract as much liquid as possible. Stir in cooled sugar syrup. Refrigerate until chilled, about 2 hours.","Process sorbet in ice cream maker according to manufacturer’s instructions. Transfer sorbet to bowl. Cover and freeze. (Sorbet can be made 1 week ahead. Keep frozen.)"],"reviewsCount":3,"willMakeAgainPct":100},{"id":"54a452506529d92b2c01f25c","dek":"Pumpkins may be all the rage just now, but we've noticed another squash that's garnering a lot of attention lately. The inconspicuous kabocha squash—too bumpy, squat, and unseasonably green to be taken seriously as porch décor—is finally being hailed for its inner beauty. With deeply flavored meat more fiery orange than that of its famous cousin, the kabocha caught the attention of several readers, all of whom wrote to request recipes from various restaurants for kabocha soup. Such an incipient following may portend great things. Is there a Great Kabocha? Not yet, Charlie Brown, but here's a great kabocha soup.\nActive time: 30 min Start to finish: 1 1/2 hr","hed":"Roasted Kabocha Squash Soup with Pancetta and Sage","pubDate":"2004-08-20T04:00:00.000Z","author":[],"type":"recipe","url":"/recipes/food/views/roasted-kabocha-squash-soup-with-pancetta-and-sage-104012","photoData":{"id":"56746183b47c050a284a4e15","filename":"EP_12162015_placeholders_formal.jpg","caption":"Menu Placeholder 2","credit":"Photo by Chelsea Kyle, Prop Styling by Rhoda Boone","colors":{"average":"#000000"},"type":"photo"},"tag":{"category":"type","name":"Soup/Stew","url":"","photosBadgeAltText":"","photosBadgeFileName":"","photosBadgeID":"","photosBadgeRelatedUri":""},"aggregateRating":3.35,"ingredients":["1 (4-lb) kabocha squash, halved and seeded","1 cup vegetable oil","20 whole fresh sage leaves plus 1 1/2 teaspoons chopped fresh sage","","1/4 lb sliced pancetta, coarsely chopped","1 tablespoon olive oil","1 large onion, chopped","2 garlic cloves, minced","3 1/2 cups chicken broth","3 1/2 cups water","1 tablespoon red-wine vinegar"],"prepSteps":["Preheat oven to 400°F.","Roast squash, cut sides down, in an oiled roasting pan in middle of oven until tender, about 1 hour. When cool enough to handle, scrape flesh from skin.","Heat vegetable oil in a deep small saucepan until it registers 365°F on a deep-fat thermometer. Fry sage leaves in 3 batches until crisp, 3 to 5 seconds. Transfer leaves with a slotted spoon to paper towels to drain.","Cook pancetta in a 4-quart heavy pot over moderate heat, stirring, until browned. Transfer pancetta with slotted spoon to paper towels to drain.","Add olive oil to pancetta fat remaining in pot, then cook onion, stirring, until softened. Stir in garlic and chopped sage and cook, stirring, until fragrant, about 1 minute. Add squash, broth, and water and simmer 20 minutes to blend flavors.","Purée soup in batches in a blender, transferring to a bowl. (Use caution when blending hot liquids.) Return soup to pot and reheat. If necessary, thin to desired consistency with water.","Stir in vinegar and salt and pepper to taste.","Serve sprinkled with pancetta and fried sage leaves."],"reviewsCount":19,"willMakeAgainPct":65},{"id":"54a4524f6529d92b2c01f250","dek":"Big chunks of portobello and shiitake mushrooms make for a hearty soup.","hed":"Creamy Roasted Mushroom Soup","pubDate":"2004-08-20T04:00:00.000Z","author":[],"type":"recipe","url":"/recipes/food/views/creamy-roasted-mushroom-soup-107252","photoData":{"id":"56746182accb4c9831e45e0a","filename":"EP_12162015_placeholders_rustic.jpg","caption":"Menu Placeholder 3","credit":"Photo by Chelsea Kyle, Prop Styling by Anna Stockwell","colors":{"average":"#000000"},"type":"photo"},"tag":{"category":"cuisine","name":"American","url":"","photosBadgeAltText":"","photosBadgeFileName":"","photosBadgeID":"","photosBadgeRelatedUri":""},"aggregateRating":3.46,"ingredients":["1 pound portobello mushrooms, stemmed, dark gills removed, caps cut into 3/4-inch pieces","1/2 pound shiitake mushrooms, stemmed, caps cut into 3/4-inch pieces","6 tablespoons olive oil","3 14-ounce cans (or more) vegetable broth","1 1/2 tablespoons butter","1 onion, chopped","3 garlic cloves, minced","1/4 cup plus 2 tablespoons Madeira","3 tablespoons all purpose flour","1 cup whipping cream","3/4 teaspoon chopped fresh thyme"],"prepSteps":["Preheat oven to 400°F. Line 2 large baking sheets with foil. Divide mushrooms between prepared baking sheets. Drizzle mushrooms on each sheet with 3 tablespoons oil. Sprinkle generously with salt and pepper; toss to coat. Cover with foil. Bake mushrooms 30 minutes. Uncover and continue baking until mushrooms are tender and still moist, about 15 minutes longer. Cool slightly. Puree half of mushrooms with 1 can broth in blender until smooth. Set mushroom puree aside.","Melt butter in heavy large pot over medium-high heat. Add onion and garlic and sauté until onion is tender, about 8 minutes. Add Madeira and simmer until almost all of liquid evaporates, about 2 minutes. Add flour; stir 2 minutes. Add 2 cans broth, cream, and thyme. Stir in remaining cooked mushroom pieces and mushroom puree. Simmer over medium heat until slightly thickened, about 10 minutes. Season soup to taste with salt and pepper. (Can be made 1 day ahead. Cool slightly, then cover and refrigerate. Bring to simmer before serving, thinning with additional broth if necessary.)"],"reviewsCount":147,"willMakeAgainPct":91},{"id":"54a4524f19925f464b38eadd","dek":"Jambon au Sirop d'Erable\nActive time: 20 min Start to finish: 4 hr","hed":"Ham Braised with Maple Raisin Sauce","pubDate":"2004-08-20T04:00:00.000Z","author":[],"type":"recipe","url":"/recipes/food/views/ham-braised-with-maple-raisin-sauce-105594","photoData":{"id":"5674617e47d1a28026045e4f","filename":"EP_12162015_placeholders_casual.jpg","caption":"Menu Placeholder 4","credit":"Photo by Chelsea Kyle, Prop Styling by Rhoda Boone","colors":{"average":"#000000"},"type":"photo"},"tag":{"category":"cuisine","name":"American","url":"","photosBadgeAltText":"","photosBadgeFileName":"","photosBadgeID":"","photosBadgeRelatedUri":""},"aggregateRating":3.17,"ingredients":["1 (7- to 8-lb) fully cooked bone-in shank-end ham","6 cups water","1/4 cup pure maple syrup","1 cup granulated maple sugar*","1 teaspoon dry mustard","1/4 cup apple juice","1/4 teaspoon ground cloves (or 10 cloves stuck into ham)","2 cups raisins (10 oz)"],"prepSteps":["Put ham cut side down in a large deep heavy pot (about 10 quarts) and add water and syrup.","Bring liquid to a boil, then reduce heat to low and gently simmer ham, covered, until tender, 2 to 2 1/2 hours. Uncover and cool slightly.","Preheat oven to 350°F.","When ham is cool enough to handle, remove from pot, reserving cooking liquid, then cut off any rind and excess fat, leaving a thin layer. Transfer ham to a roasting pan.","Whisk together sugar, mustard, apple juice, and ground cloves, if using, in a bowl, then spoon over ham. Add raisins and 1 cup reserved cooking liquid to roasting pan and bake in middle of oven, basting occasionally, until ham is glazed and juices are bubbling, 30 to 40 minutes. Serve warm or at room temperature."],"reviewsCount":11,"willMakeAgainPct":80},{"id":"54a4524e6529d92b2c01f247","dek":"The thing Hom likes most about this dessert is the contrast of the warm, sweet fruit and the cold, tangy crème fraîche.\nActive time: 15 min Start to finish: 20 min","hed":"Warm Fruit Compote with Lemon Verbena and Crème Fraîche","pubDate":"2004-08-20T04:00:00.000Z","author":[],"type":"recipe","url":"/recipes/food/views/warm-fruit-compote-with-lemon-verbena-and-creme-fraiche-104009","photoData":{"id":"5674617eb47c050a284a4e11","filename":"EP_12162015_placeholders_bright.jpg","caption":"Menu Placeholder 1","credit":"Photo by Chelsea Kyle, Prop Styling by Anna Stockwell","colors":{"average":"#000000"},"type":"photo"},"tag":{"category":"ingredient","name":"Dairy","url":"","photosBadgeAltText":"","photosBadgeFileName":"","photosBadgeID":"","photosBadgeRelatedUri":""},"aggregateRating":0,"ingredients":["1 vanilla bean, halved lengthwise","1 cup sugar","2 cups water","1/2 cup fresh lemon verbena or mint","24 small whole (Mediterranean) dried apricots (6 oz)","1 1/2 lb firm apples such as Gala, Empire, or Golden Delicious","2 tablespoons unsalted butter","Accompaniment: crème fraîche"],"prepSteps":["Scrape seeds from vanilla bean with point of a paring knife into a 5- to 6-quart wide saucepan (a wide pan minimizes breakage of apples) and add pod, sugar, water, and lemon verbena. Simmer, stirring until sugar is dissolved, 10 minutes. Add apricots and a pinch of salt and simmer, partially covered, until tender, about 10 minutes.","While apricots are simmering, peel and core apples and cut each into eighths. Add apples to syrup and simmer, uncovered, until just tender, 5 to 7 minutes. Remove from heat and stir in butter until melted."],"reviewsCount":0,"willMakeAgainPct":0},{"id":"54a4524e6529d92b2c01f241","dek":"","hed":"Crispy Noodle Pancake","pubDate":"2004-08-20T04:00:00.000Z","author":[],"type":"recipe","url":"/recipes/food/views/crispy-noodle-pancake-105593","photoData":{"id":"56746183b47c050a284a4e15","filename":"EP_12162015_placeholders_formal.jpg","caption":"Menu Placeholder 2","credit":"Photo by Chelsea Kyle, Prop Styling by Rhoda Boone","colors":{"average":"#000000"},"type":"photo"},"tag":{"category":"cuisine","name":"Asian","url":"","photosBadgeAltText":"","photosBadgeFileName":"","photosBadgeID":"","photosBadgeRelatedUri":""},"aggregateRating":3.14,"ingredients":["6 ounces fresh chow mein noodles","4 green onions, chopped","1 teaspoon plus 1 1/2 tablespoons vegetable oil","1 1/2 tablespoons oriental sesame oil"],"prepSteps":["Cook noodles in large pot of boiling water 1 1/2 minutes, stirring occasionally. Drain. Rinse with cold water. Drain well. Toss with green onions, 1 teaspoon vegetable oil, and pepper in bowl.","Heat 1 1/2 tablespoons vegetable oil and sesame oil in a heavy 9-inch nonstick skillet over medium heat. Add noodles and flatten slightly. Cook without stirring until light brown, about 6 minutes. Turn and cook second side until light brown, 6 minutes. Drain on paper towels. Cut into wedges."],"reviewsCount":7,"willMakeAgainPct":100},{"id":"54a4524d19925f464b38eac8","dek":"Active time: 10 min Start to finish: 50 min","hed":"Basmati Rice","pubDate":"2004-08-20T04:00:00.000Z","author":[],"type":"recipe","url":"/recipes/food/views/basmati-rice-104008","photoData":{"id":"56746182accb4c9831e45e0a","filename":"EP_12162015_placeholders_rustic.jpg","caption":"Menu Placeholder 3","credit":"Photo by Chelsea Kyle, Prop Styling by Anna Stockwell","colors":{"average":"#000000"},"type":"photo"},"tag":{"category":"cuisine","name":"Indian","url":"","photosBadgeAltText":"","photosBadgeFileName":"","photosBadgeID":"","photosBadgeRelatedUri":""},"aggregateRating":0,"ingredients":["2 cups basmati rice","3 cups water"],"prepSteps":["Wash rice in several changes of water, rubbing grains and letting them settle before pouring off water, until water runs clear. Drain well in a sieve.","Bring rice and water to a boil in a 3-quart heavy saucepan. Reduce heat to very low and cook, covered, until water is absorbed and rice is tender, 15 to 20 minutes.","Remove from heat and let stand, covered, 10 minutes. Fluff gently with a fork.","Put rice and water in a 3-quart microwave-safe dish and cook, uncovered, on high power 15 minutes, or until steam holes appear in rice. Cover dish with a microwave-safe lid or plate and cook on high 5 minutes more.","Let rice stand, covered, 5 minutes. Fluff gently with a fork.","If using rice for preceding fried-rice recipe, chill, covered, 8 hours."],"reviewsCount":0,"willMakeAgainPct":0},{"id":"54a4524d19925f464b38eabe","dek":"","hed":"Pan-Seared Tilapia with Chile Lime Butter","pubDate":"2004-08-20T04:00:00.000Z","author":[],"type":"recipe","url":"/recipes/food/views/pan-seared-tilapia-with-chile-lime-butter-108343","photoData":{"id":"560df8dc7b55306961bfe82d","filename":"108343.jpg","caption":"Pan-Seared Tilapia with Chile Lime Butter","credit":"Tina Rupp","promoTitle":"Pan-Seared Tilapia with Chile Lime Butter","title":"Pan-Seared Tilapia with Chile Lime Butter","orientation":"portrait","restrictCropping":false},"tag":{"category":"cuisine","name":"Asian","url":"","photosBadgeAltText":"","photosBadgeFileName":"","photosBadgeID":"","photosBadgeRelatedUri":""},"aggregateRating":3.61,"ingredients":["1/2 stick (1/4 cup) unsalted butter, softened","1 tablespoon finely chopped shallot","1 teaspoon finely grated fresh lime zest","2 teaspoons fresh lime juice","1 teaspoon minced fresh Thai or serrano chile (preferably red), including seeds","1/2 teaspoon salt","6 (5- to 6-oz) pieces skinless tilapia fillet or farm-raised striped bass fillets with skin","1/2 teaspoon salt","2 tablespoons vegetable oil"],"prepSteps":["Stir together butter, shallot, zest, lime juice, chile, and salt in a bowl.","If using striped bass, score skin in 3 or 4 places with a thin sharp knife to prevent fish from curling (do not cut through flesh). Pat fish dry and sprinkle with salt. Heat 1 tablespoon oil in a 12-inch nonstick skillet over moderately high heat until just smoking, then sauté 3 pieces of fish, turning over once with a spatula, until golden and just cooked through, 4 to 5 minutes, and transfer to a plate. Sauté remaining fish in remaining tablespoon oil in same manner.","Serve each piece of fish with a dollop of chile lime butter."],"reviewsCount":497,"willMakeAgainPct":93},{"id":"54a4524d19925f464b38eabc","dek":"Active time: 20 min Start to finish: 40 min","hed":"Baked Flounder with Tomato Caper Sauce","pubDate":"2004-08-20T04:00:00.000Z","author":[],"type":"recipe","url":"/recipes/food/views/baked-flounder-with-tomato-caper-sauce-105592","photoData":{"id":"5674617e47d1a28026045e4f","filename":"EP_12162015_placeholders_casual.jpg","caption":"Menu Placeholder 4","credit":"Photo by Chelsea Kyle, Prop Styling by Rhoda Boone","colors":{"average":"#000000"},"type":"photo"},"tag":{"category":"cuisine","name":"American","url":"","photosBadgeAltText":"","photosBadgeFileName":"","photosBadgeID":"","photosBadgeRelatedUri":""},"aggregateRating":3.44,"ingredients":["2 tablespoons olive oil","1 medium onion, finely chopped","1 cup finely chopped fennel bulb (sometimes called anise)","1 garlic clove, thinly sliced","1 (14 1/2-oz) can diced tomatoes including juice","1/4 cup dry white wine","2 tablespoons capers, rinsed and drained","1/4 teaspoon salt","1/8 teaspoon black pepper","1/2 cup fine dry bread crumbs","3 tablespoons unsalted butter, well softened","1/4 teaspoon salt","1/8 teaspoon black pepper","4 (6-oz) pieces skinless flounder or sole fillet","2 tablespoons dry white wine"],"prepSteps":["Preheat oven to 425°F.","Heat oil in a 12-inch heavy skillet over moderately high heat until hot but not smoking, then sauté onion and fennel, stirring, until golden, about 8 minutes. Add garlic and sauté, stirring, 30 seconds. Add tomatoes and wine and simmer briskly until liquid is reduced by one third, about 5 minutes. Stir in capers, salt, and pepper, then transfer to a 2-quart gratin dish or other wide shallow baking dish.","Stir together bread crumbs, butter, salt, and pepper with a fork until combined. Season flounder with salt and pepper, then roll each fillet, skinned side up, into a cylinder and arrange, seam side down, on top of sauce. Gently press bread crumbs onto flounder.","Drizzle wine carefully around fish into sauce (not over fish) and bake in middle of oven until fish is just cooked through, 20 to 25 minutes."],"reviewsCount":102,"willMakeAgainPct":95},{"id":"54a4524c6529d92b2c01f223","dek":"Brining results in moist, tender meat. Be sure to use a large center-cut loin, which cooks more evenly than two smaller pieces tied together. Begin this recipe one day ahead. What to drink: A medium-bodied fruity red, such as Merlot, or a fruity white, such as Australian Sémillon.","hed":"Brined Pork Loin with Onion, Raisin, and Garlic Compote","pubDate":"2004-08-20T04:00:00.000Z","author":[],"type":"recipe","url":"/recipes/food/views/brined-pork-loin-with-onion-raisin-and-garlic-compote-106313","photoData":{"id":"560ea0abf9a84192308a9319","filename":"106313.jpg","caption":"Brined Pork Loin with Onion, Raisin, and Garlic Compote","credit":"Brian Leatart","promoTitle":"Brined Pork Loin with Onion, Raisin, and Garlic Compote","title":"Brined Pork Loin with Onion, Raisin, and Garlic Compote","orientation":"portrait","restrictCropping":false},"tag":{"category":"cuisine","name":"American","url":"","photosBadgeAltText":"","photosBadgeFileName":"","photosBadgeID":"","photosBadgeRelatedUri":""},"aggregateRating":3.65,"ingredients":["8 cups water","1/2 cup coarse salt","1/2 cup (packed) golden brown sugar","1 tablespoon fennel seeds","1 tablespoon coriander seeds","1 tablespoon whole black peppercorns","3 bay leaves","1 center-cut boneless pork loin roast (about 4 pounds)","1 tablespoon olive oil","2 teaspoons chopped fresh sage","2 teaspoons chopped fresh rosemary","2 teaspoons chopped fresh thyme","2 teaspoons chopped fresh marjoram","Onion, Raisin, and Garlic Compote"],"prepSteps":["Combine first 7 ingredients in heavy large pot. Bring to simmer over medium heat, stirring to dissolve salt and sugar. Remove from heat. Cool to room temperature. Transfer brine to very large bowl. Add pork (weight pork with plate to keep below surface). Cover; refrigerate over-night. Drain pork. Return pork to bowl; cover with water (weight pork with plate). Soak at room temperature 2 hours.","Position rack in top third of oven and preheat to 350°F. Drain pork. Pat dry. Transfer to rack set in large roasting pan. Rub pork all over with oil. Sprinkle with fresh herbs, pressing to adhere. Sprinkle with pepper. Roast until thermometer inserted into center of pork registers 150°F, about 1 hour 40 minutes. Transfer pork to cutting board; tent with foil. Let stand 10 minutes.","Cut pork into 1/4- to 1/2-inch-thick slices. Serve with compote."],"reviewsCount":47,"willMakeAgainPct":89},{"id":"54a4524c19925f464b38eab6","dek":"","hed":"Gingered Watermelon and Yellow Tomato Salad","pubDate":"2004-08-20T04:00:00.000Z","author":[],"type":"recipe","url":"/recipes/food/views/gingered-watermelon-and-yellow-tomato-salad-15126","photoData":{"id":"5674617eb47c050a284a4e11","filename":"EP_12162015_placeholders_bright.jpg","caption":"Menu Placeholder 1","credit":"Photo by Chelsea Kyle, Prop Styling by Anna Stockwell","colors":{"average":"#000000"},"type":"photo"},"tag":{"category":"cuisine","name":"American","url":"","photosBadgeAltText":"","photosBadgeFileName":"","photosBadgeID":"","photosBadgeRelatedUri":""},"aggregateRating":3.4,"ingredients":["a 4-pound piece watermelon (preferably seedless)","2 pounds vine-ripened tomatoes (about 6 medium; preferably yellow)","1 teaspoon coarse salt (preferably sea salt)","1/2 small red onion","2 tablespoons fresh lime juice, or to taste","1 teaspoon finely grated fresh gingerroot","1/2 teaspoon sugar"],"prepSteps":["Remove rind and any seeds from watermelon. Cut fruit into 1 1/2-inch pieces and put in a large bowl. Cut tomatoes into 1 1/2-inch pieces. Add tomatoes and salt to watermelon, tossing to combine. Let mixture stand at cool room temperature 3 hours.","In a colander set over a small saucepan drain mixture and transfer to a bowl. Simmer liquid until reduced to about 2 tablespoons and cool completely. Halve onion and thinly slice enough to measure 1/4 cup. Add onion to watermelon mixture. (For best results do not chill salad, as it will lose flavor.) In a small bowl stir together reduced watermelon-tomato juice, lime juice, gingerroot, and sugar.","Just before serving, toss salad with juice mixture."],"reviewsCount":4,"willMakeAgainPct":80},{"id":"54a4524b6529d92b2c01f21c","dek":"Before spooning yogurt out of the carton, pour off any liquid on top. If you use a particularly thick yogurt, you may need to thin the sauce with a little water.","hed":"Open-Face Lamb Burgers with Mint Yogurt Sauce","pubDate":"2004-08-20T04:00:00.000Z","author":[],"type":"recipe","url":"/recipes/food/views/open-face-lamb-burgers-with-mint-yogurt-sauce-108342","photoData":{"id":"560df8dcf9a84192308a8cca","filename":"108342.jpg","caption":"Open-Face Lamb Burgers with Mint Yogurt Sauce","credit":"Romulo Yanes","promoTitle":"Open-Face Lamb Burgers with Mint Yogurt Sauce","title":"Open-Face Lamb Burgers with Mint Yogurt Sauce","orientation":"landscape","restrictCropping":false},"tag":{"category":"cuisine","name":"American","url":"","photosBadgeAltText":"","photosBadgeFileName":"","photosBadgeID":"","photosBadgeRelatedUri":""},"aggregateRating":3.65,"ingredients":["1 cup plain yogurt","1 cup loosely packed whole fresh mint leaves plus 2 tablespoons minced","1 teaspoon fresh lemon juice","1 garlic clove, halved lengthwise","1 1/2 lb ground lamb (not lean)","1/3 cup minced fresh parsley","1/4 cup minced onion","3/4 teaspoon salt","1/2 teaspoon black pepper","1/8 teaspoon ground allspice","4 (1/2-inch-thick) slices country-style bread (from a crusty round loaf; preferably 6 inches in diameter)","2 tablespoons plus 1 teaspoon extra-virgin olive oil","2 oz mesclun (3 cups)"],"prepSteps":["Prepare grill for cooking. If using a charcoal grill, open vents on bottom of grill, then light charcoal. Charcoal fire is medium-hot when you can hold your hand 5 inches above rack for 3 to 4 seconds. If using a gas grill, preheat burners on high, covered, 10 minutes, then reduce heat to moderately high.","While grill heats, whisk together yogurt, minced mint, lemon juice, and salt to taste. Mince 1 half of garlic clove and whisk into yogurt sauce.","Mix lamb, parsley, onion, salt, pepper, and allspice with your hands in a bowl until just combined (do not overwork mixture or patties will be tough). Form into 4 (4 1/2-inch) patties (1/2 inch thick).","Brush both sides of bread slices with 2 tablespoons oil (total for all slices) and grill, covered only if using a gas grill, turning over once, until golden, 1 to 2 minutes total. Rub 1 side of each toast with cut side of remaining garlic and season with salt.","Grill patties on lightly oiled grill rack, covered only if using a gas grill, turning over once, until browned but still slightly pink in center, 5 to 7 minutes total.","Toss together mesclun, whole mint leaves, remaining teaspoon oil, and salt and pepper to taste. Divide lamb among toasts on plates, then spoon sauce over and top with greens."],"reviewsCount":18,"willMakeAgainPct":100}],"numFound":34975,"page":{"generatedAt":"2017-10-11T18:50:41.292Z","count":1944,"number":1110,"size":18,"totalCount":34975,"nextUri":"/api/search/v1/query?size=18&content=recipe&page=1111&xhr=true&q","previousUri":"/api/search/v1/query?size=18&content=recipe&page=1109&xhr=true&q"},"resultGroupDisplaySize":18,"spellcheck":{"requested":""}}